[
  {
    "Title": "Coffee Beans",
    "Name": "Admin",
    "Room": 1,
    "Category": 1,
    "Priority": 5,
    "CreatedOn": "2023-02-10"
  },
  {
    "Title": "Whiteboard Markers",
    "Name": "John",
    "Room": 0,
    "Category": 0,
    "Priority": 7,
    "CreatedOn": "2023-03-15"
  },
  {
    "Title": "Hand Soap",
    "Name": "Admin",
    "Room": 2,
    "Category": 2,
    "Priority": 6,
    "CreatedOn": "2023-04-20"
  },
  {
    "Title": "Projector",
    "Name": "Admin",
    "Room": 0,
    "Category": 0,
    "Priority": 9,
    "CreatedOn": "2023-05-25"
  },
  {
    "Title": "Tortillas",
    "Name": "Admin",
    "Room": 1,
    "Category": 1,
    "Priority": 5,
    "CreatedOn": "2023-12-20"
  },
  {
    "Title": "Bananas",
    "Name": "Admin",
    "Room": 1,
    "Category": 1,
    "Priority": 6,
    "CreatedOn": "2023-12-21"
  },
  {
    "Title": "Peanuts",
    "Name": "Admin",
    "Room": 1,
    "Category": 1,
    "Priority": 5,
    "CreatedOn": "2023-12-21"
  },
  {
    "Title": "Cucumbers",
    "Name": "Admin",
    "Room": 1,
    "Category": 1,
    "Priority": 2,
    "CreatedOn": "2023-12-21"
  },
  {
    "Title": "Power Bank",
    "Name": "Admin",
    "Room": 0,
    "Category": 0,
    "Priority": 10,
    "CreatedOn": "2023-12-21"
  },
  {
    "Title": "Raisins",
    "Name": "Admin",
    "Room": 1,
    "Category": 1,
    "Priority": 1,
    "CreatedOn": "2023-12-21"
  },
  {
    "Title": "Sun Screen",
    "Name": "Admin",
    "Room": 2,
    "Category": 2,
    "Priority": 4,
    "CreatedOn": "2023-12-21"
  },
  {
    "Title": "TV",
    "Name": "Admin",
    "Room": 0,
    "Category": 0,
    "Priority": 7,
    "CreatedOn": "2023-12-21"
  },
  {
    "Title": "TV Remote",
    "Name": "Admin",
    "Room": 0,
    "Category": 0,
    "Priority": 3,
    "CreatedOn": "2023-12-21"
  },
  {
    "Title": "AAA Batteries",
    "Name": "Admin",
    "Room": 0,
    "Category": 0,
    "Priority": 8,
    "CreatedOn": "2023-12-21"
  },
  {
    "Title": "Newspaper",
    "Name": "Mike",
    "Room": 0,
    "Category": 2,
    "Priority": 1,
    "CreatedOn": "2023-12-22"
  },
  {
    "Title": "Wireless Mouse",
    "Name": "Mike",
    "Room": 0,
    "Category": 0,
    "Priority": 2,
    "CreatedOn": "2023-12-22"
  },
  {
    "Title": "Wireless Remote",
    "Name": "Mike",
    "Room": 1,
    "Category": 0,
    "Priority": 7,
    "CreatedOn": "2023-12-22"
  },
  {
    "Title": "Something odd",
    "Name": "Admin",
    "Room": 2,
    "Category": 1,
    "Priority": 2,
    "CreatedOn": "2023-12-22"
  }
]